mint/__init__.py
mint/brand_svd.py
mint/cli.py
mint/device.py
mint/extract.py
mint/logits.py
mint/low_rank_layer.py
mint/safetensors.py
mint/semantic_redistributor.py
mint/similarity.py
mint/sr_layer.py
mint/utils.py
mint/wrapper.py
mint_llm-0.1.4.dist-info/METADATA
mint_llm-0.1.4.dist-info/WHEEL
mint_llm-0.1.4.dist-info/entry_points.txt
mint_llm-0.1.4.dist-info/top_level.txt
mint_llm-0.1.4.dist-info/RECORD
