Metadata-Version: 2.4
Name: mint-llm
Version: 0.1.4
Summary: Meaning-Informed Next-token Transformation
Author-email: Bryan O'Malley <bo122081@hotmail.com>
Project-URL: pypi, https://pypi.org/project/mint-llm/
Keywords: llm,machine learning,text-generation,huggingface,hf,pytorch,tools,svd,isvd
Classifier: Development Status :: 2 - Pre-Alpha
Classifier: Environment :: Console
Classifier: Intended Audience :: Developers
Classifier: Topic :: Scientific/Engineering :: Artificial Intelligence
Requires-Python: >=3.13
Requires-Dist: huggingface-hub
Requires-Dist: numpy
Requires-Dist: peft
Requires-Dist: safetensors
Requires-Dist: torch>=2.7
Requires-Dist: tqdm
Requires-Dist: transformers
Requires-Dist: typer
Provides-Extra: dev
Requires-Dist: black; extra == "dev"
Requires-Dist: black[jupyter]; extra == "dev"
Requires-Dist: cffconvert; extra == "dev"
Requires-Dist: ipykernel; extra == "dev"
Requires-Dist: mypy; extra == "dev"
Requires-Dist: pytest; extra == "dev"
Requires-Dist: ruff; extra == "dev"
Requires-Dist: types-tqdm; extra == "dev"
Requires-Dist: vulkan; extra == "dev"
